[
    {
        "cardImg": "https://vertical.pstatic.net/vertical-cardad/creatives/KB/1692/KB_1692_20230125-142003_hor.png",
        "cardName": "KB국민 청춘대로 톡톡카드",
        "cardDesc": "스타벅스 최대 60%할인은 기본",
        "cardAnnual": "국내 1만원, 해외 1만2천원"
    },
    {
        "cardImg": "https://vertical.pstatic.net/vertical-cardad/creatives/KB/115/KB_115_20230125-142026_hor.png",
        "cardName": "KB국민 굿데이카드",
        "cardDesc": "통신·교통·외식 등 생활영역10%할인",
        "cardAnnual": "국내 5천원, 해외 1만원"
    },
    {
        "cardImg": "https://vertical.pstatic.net/vertical-cardad/creatives/KB/10216/KB_10216_20240314-135529_hor.png",
        "cardName": "KB국민 My WE:SH 카드",
        "cardDesc": "음식점최대20%, OTT30% 할인",
        "cardAnnual": "국내 1만5천원, 해외 1만5천원"
    },
    {
        "cardImg": "https://vertical.pstatic.net/vertical-cardad/creatives/KB/1294/KB_1294_20230308-153427_hor.png",
        "cardName": "KB국민 굿데이올림카드",
        "cardDesc": "연회비 만오천원에 연최대94만8천원!",
        "cardAnnual": "국내 1만5천원, 해외 2만원"
    },
    {
        "cardImg": "https://vertical.pstatic.net/vertical-cardad/creatives/KB/3717/KB_3717_20230308-152833_hor.png",
        "cardName": "KB국민 Easy all 티타늄카드",
        "cardDesc": "많이 쓴 영역 알아서 자동 캐시백!",
        "cardAnnual": "국내 3만원, 해외 3만원"
    },
    {
        "cardImg": "https://vertical.pstatic.net/vertical-cardad/creatives/KB/2332/KB_2332_20230215-134842_hor.png",
        "cardName": "KB국민 톡톡Pay카드",
        "cardDesc": "간편결제(Pay) 청구할인 최대40%",
        "cardAnnual": "국내 2만원, 해외 2만원"
    },
    {
        "cardImg": "https://vertical.pstatic.net/vertical-cardad/creatives/KB/1470/KB_1470_20231024-103817_hor.png",
        "cardName": "KB국민 가온글로벌카드",
        "cardDesc": "해외가맹점 최대 3% 포인트리 적립",
        "cardAnnual": "국내 1만5천원, 해외 2만원"
    },
    {
        "cardImg": "https://vertical.pstatic.net/vertical-cardad/creatives/KB/10302/KB_10302_20231115-181801_hor.png",
        "cardName": "아메리칸 익스프레스 블루 KB국민카드",
        "cardDesc": "쇼핑·주유·편의점 등 생활영역 할인",
        "cardAnnual": "국내 1만9천원, 해외 1만9천원"
    },
    {
        "cardImg": "https://vertical.pstatic.net/vertical-cardad/creatives/KB/99/KB_99_20230308-153721_hor.png",
        "cardName": "KB국민 와이즈카드",
        "cardDesc": "많이 쓴 곳 알아서 최대 5%적립",
        "cardAnnual": "국내 5천원, 해외 1만원"
    },
    {
        "cardImg": "https://vertical.pstatic.net/vertical-cardad/creatives/KB/10332/KB_10332_20240322-101950_ver.png",
        "cardName": "KB국민 WE:SH Travel 카드",
        "cardDesc": "이용실적 없이 해외 이용 수수료 면제",
        "cardAnnual": "국내 2만5천원, 해외 2만5천원"
    },
    {
        "cardImg": "https://vertical.pstatic.net/vertical-cardad/creatives/KB/10221/KB_10221_20230203-141842_ver.png",
        "cardName": "HERITAGE Smart [대한항공 마일리지형]",
        "cardDesc": "대한항공 및 저가항공사 15만원할인!",
        "cardAnnual": "국내 20만원, 해외 20만원"
    },
    {
        "cardImg": "https://vertical.pstatic.net/vertical-cardad/creatives/KB/2916/KB_2916_20230127-104432_hor.png",
        "cardName": "KB국민 BeV V카드(스카이패스형)",
        "cardDesc": "스카이패스 1500원당 최대3마일적립",
        "cardAnnual": "국내 29만5천원, 해외 30만원"
    },
    {
        "cardImg": "https://vertical.pstatic.net/vertical-cardad/creatives/KB/1316/KB_1316_20230308-153352_hor.png",
        "cardName": "KB국민 가온올림카드(실속형)",
        "cardDesc": "무실적 전가맹 0.7% 기본적립",
        "cardAnnual": "국내 1만5천원, 해외 1만5천원"
    },
    {
        "cardImg": "https://vertical.pstatic.net/vertical-cardad/creatives/KB/10301/KB_10301_20231115-161338_hor.png",
        "cardName": "아메리칸 익스프레스 로즈골드 KB국민카드",
        "cardDesc": "KB Pay 결제시 최대 10% 할인",
        "cardAnnual": "국내 1만9천원, 해외 1만9천원"
    },
    {
        "cardImg": "https://vertical.pstatic.net/vertical-cardad/creatives/KB/2612/KB_2612_20240126-104113_hor.png",
        "cardName": "KB국민 The Easy카드",
        "cardDesc": "대형마트·주유소 최대 5.7% 할인",
        "cardAnnual": "국내 1만5천원, 해외 1만5천원"
    },
    {
        "cardImg": "https://vertical.pstatic.net/vertical-cardad/creatives/KB/1451/KB_1451_20240126-112342_hor.png",
        "cardName": "KB국민 다담카드",
        "cardDesc": "교통·통신10%,주유L당60원할인",
        "cardAnnual": "국내 1만5천원, 해외 2만원"
    },
    {
        "cardImg": "https://vertical.pstatic.net/vertical-cardad/creatives/KB/1362/KB_1362_20230127-093050_hor.png",
        "cardName": "KB국민 FINETECH카드(마일리지 아시아나)",
        "cardDesc": "국내가맹점 1천원당 최대 3마일 적립",
        "cardAnnual": "국내 2만원, 해외 2만5천원"
    },
    {
        "cardImg": "https://vertical.pstatic.net/vertical-cardad/creatives/KB/1361/KB_1361_20230125-142108_hor.png",
        "cardName": "KB국민 FINETECH카드(마일리지 대한항공)",
        "cardDesc": "국내가맹점 1,500원당 최대 3마일",
        "cardAnnual": "국내 2만원, 해외 2만5천원"
    },
    {
        "cardImg": "https://vertical.pstatic.net/vertical-cardad/creatives/KB/111/KB_111_20230308-153729_hor.png",
        "cardName": "KB국민 와이즈홈카드",
        "cardDesc": "통신요금10%, 대중교통 5%청구할인",
        "cardAnnual": "국내 5천원, 해외 1만원"
    },
    {
        "cardImg": "https://vertical.pstatic.net/vertical-cardad/creatives/KB/10267/KB_10267_20240424-101143_ver.png",
        "cardName": "KB국민 K-패스카드",
        "cardDesc": "대중교통 10%, 통신비 5% 할인!",
        "cardAnnual": "국내 8천원, 해외 8천원"
    },
    {
        "cardImg": "https://vertical.pstatic.net/vertical-cardad/creatives/KB/2472/KB_2472_20230308-153950_hor.png",
        "cardName": "KB국민 탄탄대로 온리유 티타늄카드",
        "cardDesc": "주유소 리터당 최대 200점 적립",
        "cardAnnual": "국내 3만원, 해외 3만원"
    },
    {
        "cardImg": "https://vertical.pstatic.net/vertical-cardad/creatives/KB/10039/KB_10039_20230308-153417_hor.png",
        "cardName": "KB국민행복카드",
        "cardDesc": "임신중독증 등 단체보험 무료가입",
        "cardAnnual": "국내전용 없음, 해외겸용 없음"
    },
    {
        "cardImg": "https://vertical.pstatic.net/vertical-cardad/creatives/KB/3638/KB_3638_20230308-153603_hor.png",
        "cardName": "KB국민 마이핏카드(할인형)",
        "cardDesc": "외식·마트·주유·통신 등 생활영역",
        "cardAnnual": "국내 1만원, 해외 1만원"
    },
    {
        "cardImg": "https://vertical.pstatic.net/vertical-cardad/creatives/KB/10220/KB_10220_20230203-141834_ver.png",
        "cardName": "KB국민 HERITAGE Smart [할인형]",
        "cardDesc": "대한항공 및 저가항공사 15만원할인!",
        "cardAnnual": "국내 20만원, 해외 20만원"
    },
    {
        "cardImg": "https://vertical.pstatic.net/vertical-cardad/creatives/KB/2856/KB_2856_20230308-152844_hor.png",
        "cardName": "KB국민 Easy on카드",
        "cardDesc": "야놀자·여기어때·데일리호텔 5% 할인",
        "cardAnnual": "국내 2만원, 해외 2만원"
    },
    {
        "cardImg": "https://vertical.pstatic.net/vertical-cardad/creatives/KB/2696/KB_2696_20230308-153230_hor.png",
        "cardName": "KB국민 LGU+ 심플라이트카드",
        "cardDesc": "매월 최대 17,000원 할인!",
        "cardAnnual": "국내 1만5천원, 해외 1만5천원"
    },
    {
        "cardImg": "https://vertical.pstatic.net/vertical-cardad/creatives/KB/10043/KB_10043_20230308-152810_ver.png",
        "cardName": "Coffee Bean 신용카드",
        "cardDesc": "커피빈 이용 시 건당 3천원 할인",
        "cardAnnual": "국내 2만원, 해외 2만원"
    },
    {
        "cardImg": "https://vertical.pstatic.net/vertical-cardad/creatives/KB/2857/KB_2857_20230308-152855_hor.png",
        "cardName": "KB국민 Easy Pick카드",
        "cardDesc": "쇼핑·마트·주유·교통 5% 기본적립",
        "cardAnnual": "국내 2만원, 해외 2만원"
    },
    {
        "cardImg": "https://vertical.pstatic.net/vertical-cardad/creatives/KB/2486/KB_2486_20230308-152736_hor.png",
        "cardName": "KB국민 CLiP카드",
        "cardDesc": "매월 최대 1만7천원 할인",
        "cardAnnual": "국내 1만5천원, 해외 1만5천원"
    },
    {
        "cardImg": "https://vertical.pstatic.net/vertical-cardad/creatives/KB/10204/KB_10204_20230308-153936_hor.png",
        "cardName": "KB국민 쿠쿠렌탈Ⅱ카드",
        "cardDesc": "쿠쿠 렌탈료 자동납부 시 렌탈료",
        "cardAnnual": "국내 1만5천원, 해외 1만5천원"
    },
    {
        "cardImg": "https://vertical.pstatic.net/vertical-cardad/creatives/KB/1681/KB_1681_20230308-153926_hor.png",
        "cardName": "코웨이 KB국민카드",
        "cardDesc": "코웨이 렌탈비 최대 2만원 할인",
        "cardAnnual": "국내 1만원, 해외 1만5천원"
    },
    {
        "cardImg": "https://vertical.pstatic.net/vertical-cardad/creatives/KB/10203/KB_10203_20230308-153914_hor.png",
        "cardName": "KB국민 청호나이스Ⅱ카드",
        "cardDesc": "청호나이스 렌탈료 자동납부 시",
        "cardAnnual": "국내 1만5천원, 해외 1만5천원"
    },
    {
        "cardImg": "https://vertical.pstatic.net/vertical-cardad/creatives/KB/710/KB_710_20230308-153437_hor.png",
        "cardName": "KB국민 그린카드(전국형)",
        "cardDesc": "연회비없음! 쇼핑 최대 3%",
        "cardAnnual": "국내전용 없음, 해외겸용 없음"
    },
    {
        "cardImg": "https://vertical.pstatic.net/vertical-cardad/creatives/KB/10070/KB_10070_20230308-153240_hor.png",
        "cardName": "KB국민 Liiv M Ⅱ카드",
        "cardDesc": "리브M 통신비 월 최대 1만7천원할인",
        "cardAnnual": "국내 1만5천원, 해외 1만5천원"
    },
    {
        "cardImg": "https://vertical.pstatic.net/vertical-cardad/creatives/KB/3076/KB_3076_20230308-153450_hor.png",
        "cardName": "KB국민 그린카드(서울형)",
        "cardDesc": "연회비없음! 쇼핑 최대 3%",
        "cardAnnual": "국내전용 없음, 해외겸용 없음"
    },
    {
        "cardImg": "https://vertical.pstatic.net/vertical-cardad/creatives/KB/10250/KB_10250_20230413-094648_hor.png",
        "cardName": "모두렌탈 KB국민카드",
        "cardDesc": "모두렌탈 렌탈료 자동납부 시",
        "cardAnnual": "국내 1만5천원, 해외 1만5천원"
    },
    {
        "cardImg": "https://vertical.pstatic.net/vertical-cardad/creatives/KB/1680/KB_1680_20230308-153248_hor.png",
        "cardName": "KB국민 SK매직 올림카드",
        "cardDesc": "SK매직 렌탈료 최대 2만원 할인!",
        "cardAnnual": "국내 1만2천원, 해외 1만5천원"
    },
    {
        "cardImg": "https://vertical.pstatic.net/vertical-cardad/creatives/KB/2422/KB_2422_20230503-134152_hor.png",
        "cardName": "교원 웰스 KB국민카드",
        "cardDesc": "교원웰스 렌탈료 최대 2만원 할인",
        "cardAnnual": "국내 1만2천원, 해외 1만2천원"
    },
    {
        "cardImg": "https://vertical.pstatic.net/vertical-cardad/creatives/KB/2392/KB_2392_20230308-153343_hor.png",
        "cardName": "KB국민 U+ 알뜰모바일카드",
        "cardDesc": "최대 17,000원 할인!",
        "cardAnnual": "국내 1만5천원"
    },
    {
        "cardImg": "https://vertical.pstatic.net/vertical-cardad/creatives/KB/10275/KB_10275_20230810-152936_ver.png",
        "cardName": "챌린지 백 KB국민카드",
        "cardDesc": "11번가 OK캐쉬백 최대11.1%적립",
        "cardAnnual": "국내 1만5천원, 해외 1만5천원"
    },
    {
        "cardImg": "https://vertical.pstatic.net/vertical-cardad/creatives/KB/10058/KB_10058_20210817-151322_ver.png",
        "cardName": "KB국민 KB Pay 챌린지카드",
        "cardDesc": "KB Pay이용시 월 최대5만포인트리",
        "cardAnnual": "국내 1만5천원, 해외 1만5천원"
    },
    {
        "cardImg": "https://vertical.pstatic.net/vertical-cardad/creatives/KB/10059/KB_10059_20230308-152907_hor.png",
        "cardName": "KB국민 Green Wave 1.5℃ 카드",
        "cardDesc": "친환경마켓 20% 포인트리 적립",
        "cardAnnual": "국내 1만5천원, 해외 1만5천원"
    },
    {
        "cardImg": "https://vertical.pstatic.net/vertical-cardad/creatives/KB/10212/KB_10212_20230308-153221_ver.png",
        "cardName": "LFmall 신용카드",
        "cardDesc": "알뜰하게 LF몰 5% 할인 받고",
        "cardAnnual": "국내 1만5천원, 해외 1만5천원"
    },
    {
        "cardImg": "https://vertical.pstatic.net/vertical-cardad/creatives/KB/10062/KB_10062_20210617-143459_ver.png",
        "cardName": "KB국민 위메프페이 신용카드",
        "cardDesc": "위메프 2%, 위메프오 1% 적립",
        "cardAnnual": "국내 2만원, 해외 2만원"
    }
]